tcparse/__init__.py
tcparse/cli.py
tcparse/exceptions.py
tcparse/helpers.py
tcparse/main.py
tcparse/parsers.py
tcparse-0.2.1.dist-info/WHEEL
tcparse-0.2.1.dist-info/METADATA
tcparse-0.2.1.dist-info/entry_points.txt
tcparse-0.2.1.dist-info/RECORD
