Metadata-Version: 2.1
Name: tcparse
Version: 0.2.1
Summary: A package for parsing TeraChem file outputs into structured MolSSI data objects.
License: MIT
Author: Colton Hicks
Author-email: github@coltonhicks.com
Requires-Python: >=3.8.1,<4.0.0
Classifier: License :: OSI Approved :: MIT License
Classifier: Programming Language :: Python :: 3
Classifier: Programming Language :: Python :: 3.9
Classifier: Programming Language :: Python :: 3.10
Classifier: Programming Language :: Python :: 3.11
Requires-Dist: qcelemental (>=0.25.1)
